datacleaner/__init__.py
datacleaner/camelcase.py
datacleaner/datacleaner.py
datacleaner/snakecase.py
pydatacleaner-0.1.2.9.dist-info/LICENSE.txt
pydatacleaner-0.1.2.9.dist-info/METADATA
pydatacleaner-0.1.2.9.dist-info/WHEEL
pydatacleaner-0.1.2.9.dist-info/top_level.txt
pydatacleaner-0.1.2.9.dist-info/RECORD
