Metadata-Version: 2.1
Name: pydatacleaner
Version: 0.1.2.9
Summary: A utility designed to process/parse/clean scalars, especially text. (note: in active development)
Home-page: https://gitlab.com/krcrouse/datacleaner
Author: Kevin Crouse
Author-email: krcrouse@gmail.com
License: UNKNOWN
Platform: UNKNOWN
Classifier: Programming Language :: Python :: 3.7
Classifier: License :: OSI Approved :: Apache Software License
Classifier: Operating System :: OS Independent
Classifier: Development Status :: 3 - Alpha
